<?xml version="1.0" encoding="utf-8"?>
<Entity parent="template_structure_military_barracks">
  <Footprint>
    <Square width="25.0" depth="25.0"/>
    <Height>12.0</Height>
  </Footprint>
  <Health>
    <Max>2200</Max>
    <SpawnEntityOnDeath>decay|rubble/rubble_stone_5x5</SpawnEntityOnDeath>
  </Health>
  <Identity>
    <Civ>gaia</Civ>
    <SpecificName>Stratēgeîon</SpecificName>
    <History>The Stratigeion was the main military headquarters, where important decisions were taken and plans for battles discussed by the Hellene Generals, or "Strategoi".</History>
  </Identity>
  <Obstruction>
    <Static width="20.0" depth="20.0"/>
  </Obstruction>
  <ProductionQueue><ProductionQueue>
    <BatchTimeModifier>0.8</BatchTimeModifier>
    <Entities datatype="tokens">
	    -units/{civ}_infantry_spearman_militia_b
      -units/{civ}_infantry_spearman_b
      -units/{civ}_infantry_hoplite_b
      -units/{civ}_infantry_ekdromos_b
      -units/{civ}_infantry_pikeman_militia_b
      -units/{civ}_infantry_pikeman_b
      -units/{civ}_infantry_swordsman_militia_b
      -units/{civ}_infantry_swordsman_b
      -units/{civ}_infantry_swordsman_light_b
      -units/{civ}_infantry_swordsman_heavy_b
	    -units/{civ}_infantry_javelinist_militia_b
	    -units/{civ}_infantry_javelinist_light_b
	    -units/{civ}_infantry_javelinist_b
	    -units/{civ}_infantry_javelinist_merc_b
	    -units/{civ}_infantry_javelinist_heavy_b
	    -units/{civ}_infantry_slinger_militia_b
	    -units/{civ}_infantry_slinger_b
	    -units/{civ}_infantry_slinger_merc_b
	    -units/{civ}_infantry_archer_b
	    -units/{civ}_infantry_archer_merc_b
      units/{civ}_infantry_hoplite_classic_b
      units/{civ}_infantry_hoplite_light_b
      units/{civ}_infantry_hoplite_reformed_b
    </Entities>
    <Technologies datatype="tokens">
	  hellenes/health_inf_martial_arts
    </Technologies>
  </ProductionQueue>
  <VisualActor>
    <Actor>structures/athenians/barracks.xml</Actor>
    <FoundationActor>structures/fndn_5x5.xml</FoundationActor>
  </VisualActor>
</Entity>
